{
    "session_id": "1725986479",
    "timestamp": "2024-09-10T19:41:19.468904",
    "session_dir": "./User_Session/1725986479",
    "objects": [
        {
            "type": "PP",
            "confidence": 0.43926137685775757,
            "image_before": "./User_Session/1725986479/RPI_img1.jpg",
            "image_after": "./User_Session/1725986479/RPI_Prediction1.jpg"
        },
        {
            "type": "PP",
            "confidence": 0.8963351249694824,
            "image_before": "./User_Session/1725986479/RPI_img2.jpg",
            "image_after": "./User_Session/1725986479/RPI_Prediction2.jpg"
        }
    ],
    "analytics": {
        "total_objects": 2,
        "metal_objects": 0,
        "plastic_objects": 2
    }
}